{
  "source_file": "Malla-academica-HSP",
  "Last-Modified": "2026-06-08T21:01:33.187Z",
  "courses": [
    {
      "id": "MAT1009",
      "code": "MAT 1009",
      "title": "Matemática Empresarial +Ej",
      "description": "",
      "credits": 3,
      "semester": 1,
      "block": "Semestre 1",
      "area": "MAT",
      "type": "obligatoria",
      "prerequisites": [],
      "alternatives": []
    },
    {
      "id": "ECN1001",
      "code": "ECN 1001",
      "title": "Introducción a la Economía",
      "description": "",
      "credits": 3,
      "semester": 1,
      "block": "Semestre 1",
      "area": "ECN",
      "type": "obligatoria",
      "prerequisites": [],
      "alternatives": []
    },
    {
      "id": "HSP1001",
      "code": "HSP 1001",
      "title": "Introducción a la Hospitalidad",
      "description": "",
      "credits": 3,
      "semester": 1,
      "block": "Semestre 1",
      "area": "HSP",
      "type": "obligatoria",
      "prerequisites": [],
      "alternatives": []
    },
    {
      "id": "ARL1001",
      "code": "ARL 1001",
      "title": "Autoconocimiento",
      "description": "",
      "credits": 3,
      "semester": 1,
      "block": "Semestre 1",
      "area": "ARL",
      "type": "obligatoria",
      "prerequisites": [],
      "alternatives": []
    },
    {
      "id": "ARL1002",
      "code": "ARL 1002",
      "title": "Cosmos",
      "description": "",
      "credits": 3,
      "semester": 1,
      "block": "Semestre 1",
      "area": "ARL",
      "type": "obligatoria",
      "prerequisites": [],
      "alternatives": []
    },
    {
      "id": "ESL0001",
      "code": "ESL 0001",
      "title": "Inglés Nivel 1",
      "description": "",
      "credits": 0,
      "semester": 1,
      "block": "Semestre 1",
      "area": "ESL",
      "type": "obligatoria",
      "prerequisites": [],
      "alternatives": []
    },
    {
      "id": "ESL0002",
      "code": "ESL 0002",
      "title": "Inglés Nivel 2",
      "description": "",
      "credits": 0,
      "semester": 1,
      "block": "Semestre 1",
      "area": "ESL",
      "type": "obligatoria",
      "prerequisites": [
        "ESL0001"
      ],
      "alternatives": []
    },
    {
      "id": "ESP1001",
      "code": "ESP 1001",
      "title": "Escritura Académica",
      "description": "",
      "credits": 3,
      "semester": 2,
      "block": "Semestre 2",
      "area": "ESP",
      "type": "obligatoria",
      "prerequisites": [],
      "alternatives": []
    },
    {
      "id": "HSP1006",
      "code": "HSP 1006",
      "title": "Comunicación para el servicio",
      "description": "",
      "credits": 3,
      "semester": 2,
      "block": "Semestre 2",
      "area": "HSP",
      "type": "obligatoria",
      "prerequisites": [],
      "alternatives": []
    },
    {
      "id": "FIN2002",
      "code": "FIN 2002",
      "title": "Contabilidad Financiera",
      "description": "",
      "credits": 3,
      "semester": 2,
      "block": "Semestre 2",
      "area": "FIN",
      "type": "obligatoria",
      "prerequisites": [],
      "alternatives": []
    },
    {
      "id": "HSP1003",
      "code": "HSP 1003",
      "title": "Introducción al Turismo",
      "description": "",
      "credits": 3,
      "semester": 2,
      "block": "Semestre 2",
      "area": "HSP",
      "type": "obligatoria",
      "prerequisites": [],
      "alternatives": []
    },
    {
      "id": "ARL2001",
      "code": "ARL 2001",
      "title": "Ser y Cosmos",
      "description": "",
      "credits": 3,
      "semester": 2,
      "block": "Semestre 2",
      "area": "ARL",
      "type": "obligatoria",
      "prerequisites": [],
      "alternatives": []
    },
    {
      "id": "ESL0003",
      "code": "ESL 0003",
      "title": "Inglés Nivel 3",
      "description": "",
      "credits": 0,
      "semester": 2,
      "block": "Semestre 2",
      "area": "ESL",
      "type": "obligatoria",
      "prerequisites": [
        "ESL0002"
      ],
      "alternatives": []
    },
    {
      "id": "ESL0004",
      "code": "ESL 0004",
      "title": "Inglés Nivel 4",
      "description": "",
      "credits": 0,
      "semester": 2,
      "block": "Semestre 2",
      "area": "ESL",
      "type": "obligatoria",
      "prerequisites": [
        "ESL0003"
      ],
      "alternatives": []
    },
    {
      "id": "MAT2009",
      "code": "MAT 2009",
      "title": "Estadística Empresarial +Lab",
      "description": "",
      "credits": 3,
      "semester": 3,
      "block": "Semestre 3",
      "area": "MAT",
      "type": "obligatoria",
      "prerequisites": [
        "MAT1009 || MAT1009E || MAT1003"
      ],
      "alternatives": []
    },
    {
      "id": "HSP2003",
      "code": "HSP 2003",
      "title": "Introducción al Marketing HSP",
      "description": "",
      "credits": 3,
      "semester": 3,
      "block": "Semestre 3",
      "area": "HSP",
      "type": "obligatoria",
      "prerequisites": [
        "HSP1001"
      ],
      "alternatives": []
    },
    {
      "id": "GST2001",
      "code": "GST 2001",
      "title": "Servicio y Protocolo",
      "description": "",
      "credits": 3,
      "semester": 3,
      "block": "Semestre 3",
      "area": "GST",
      "type": "obligatoria",
      "prerequisites": [
        "HSP1001"
      ],
      "alternatives": []
    },
    {
      "id": "CCSS",
      "code": "CCSS",
      "title": "CCSS:HIS/SOC/ ANT /POL/REL/PSI",
      "description": "",
      "credits": 3,
      "semester": 3,
      "block": "Semestre 3",
      "area": "CCSS",
      "type": "optativa",
      "prerequisites": [],
      "alternatives": []
    },
    {
      "id": "ESL0005",
      "code": "ESL 0005",
      "title": "Inglés Nivel 5",
      "description": "",
      "credits": 0,
      "semester": 3,
      "block": "Semestre 3",
      "area": "ESL",
      "type": "obligatoria",
      "prerequisites": [
        "ESL0004"
      ],
      "alternatives": []
    },
    {
      "id": "ESL0006",
      "code": "ESL 0006",
      "title": "Inglés Nivel 6",
      "description": "",
      "credits": 0,
      "semester": 3,
      "block": "Semestre 3",
      "area": "ESL",
      "type": "obligatoria",
      "prerequisites": [
        "ESL0005"
      ],
      "alternatives": []
    },
    {
      "id": "HSP0001",
      "code": "HSP 0001",
      "title": "Coloquios",
      "description": "",
      "credits": 1,
      "semester": 4,
      "block": "Semestre 4",
      "area": "HSP",
      "type": "obligatoria",
      "prerequisites": [],
      "alternatives": []
    },
    {
      "id": "GST3004",
      "code": "GST 3004",
      "title": "Arte Culinario para Foodies",
      "description": "",
      "credits": 3,
      "semester": 4,
      "block": "Semestre 4",
      "area": "GST",
      "type": "obligatoria",
      "prerequisites": [],
      "alternatives": []
    },
    {
      "id": "ADM3002",
      "code": "ADM 3002",
      "title": "Emprendimiento",
      "description": "",
      "credits": 3,
      "semester": 4,
      "block": "Semestre 4",
      "area": "ADM",
      "type": "obligatoria",
      "prerequisites": [],
      "alternatives": []
    },
    {
      "id": "HSP1005",
      "code": "HSP 1005",
      "title": "Finanzas para Hospitalidad",
      "description": "",
      "credits": 3,
      "semester": 4,
      "block": "Semestre 4",
      "area": "HSP",
      "type": "obligatoria",
      "prerequisites": [
        "FIN2002",
        "MAT1009"
      ],
      "alternatives": []
    },
    {
      "id": "PRC2000",
      "code": "PRC 2000",
      "title": "Aprendizaje y Servicio PASEC",
      "description": "",
      "credits": 3,
      "semester": 4,
      "block": "Semestre 4",
      "area": "PRC",
      "type": "obligatoria",
      "prerequisites": [],
      "alternatives": []
    },
    {
      "id": "CIENCIAS",
      "code": "CIENCIAS",
      "title": "CC: FIS/QUI/BIO/ECL/NUT/GEO",
      "description": "",
      "credits": 3,
      "semester": 4,
      "block": "Semestre 4",
      "area": "CIENCIAS",
      "type": "obligatoria",
      "prerequisites": [],
      "alternatives": []
    },
    {
      "id": "GST0010",
      "code": "GST 0010",
      "title": "Cultura Gastronómica",
      "description": "",
      "credits": 1,
      "semester": 5,
      "block": "Semestre 5",
      "area": "GST",
      "type": "obligatoria",
      "prerequisites": [],
      "alternatives": []
    },
    {
      "id": "GST4003",
      "code": "GST 4003",
      "title": "Enología y Coctelería",
      "description": "",
      "credits": 3,
      "semester": 5,
      "block": "Semestre 5",
      "area": "GST",
      "type": "obligatoria",
      "prerequisites": [
        "GST2001"
      ],
      "alternatives": []
    },
    {
      "id": "HSP2002",
      "code": "HSP 2002",
      "title": "Operaciones Hoteleras",
      "description": "",
      "credits": 3,
      "semester": 5,
      "block": "Semestre 5",
      "area": "HSP",
      "type": "obligatoria",
      "prerequisites": [
        "HSP1001"
      ],
      "alternatives": []
    },
    {
      "id": "HSP3001",
      "code": "HSP 3001",
      "title": "Recursos Humanos HSP",
      "description": "",
      "credits": 3,
      "semester": 5,
      "block": "Semestre 5",
      "area": "HSP",
      "type": "obligatoria",
      "prerequisites": [
        "HSP1001"
      ],
      "alternatives": []
    },
    {
      "id": "OPT1",
      "code": "OPT 1",
      "title": "Optativa 1/5",
      "description": "",
      "credits": 3,
      "semester": 5,
      "block": "Semestre 5",
      "area": "OPT",
      "type": "optativa",
      "prerequisites": [],
      "alternatives": []
    },
    {
      "id": "HUM",
      "code": "HUM",
      "title": "Humanidades: LIT/FIL/ARH/ESC",
      "description": "",
      "credits": 3,
      "semester": 5,
      "block": "Semestre 5",
      "area": "HUM",
      "type": "optativa",
      "prerequisites": [],
      "alternatives": []
    },
    {
      "id": "HSP4001",
      "code": "HSP 4001",
      "title": "Gerencia Financiera HSP",
      "description": "",
      "credits": 3,
      "semester": 6,
      "block": "Semestre 6",
      "area": "HSP",
      "type": "obligatoria",
      "prerequisites": [
        "HSP2001",
        "MAT1009",
        "FIN2002",
        "HSP1005"
      ],
      "alternatives": []
    },
    {
      "id": "HSP3009",
      "code": "HSP 3009",
      "title": "Marketing de Hospitalidad",
      "description": "",
      "credits": 3,
      "semester": 6,
      "block": "Semestre 6",
      "area": "HSP",
      "type": "obligatoria",
      "prerequisites": [
        "HSP1001",
        "HSP2003 || MAK1001"
      ],
      "alternatives": []
    },
    {
      "id": "HSP3008",
      "code": "HSP 3008",
      "title": "Prácticas de Hospitalidad",
      "description": "",
      "credits": 3,
      "semester": 6,
      "block": "Semestre 6",
      "area": "HSP",
      "type": "obligatoria",
      "prerequisites": [
        "HSP1001",
        "GST2001",
        "HSP2002"
      ],
      "alternatives": []
    },
    {
      "id": "ELECTIVA1",
      "code": "ELECTIVA 1",
      "title": "Electiva Libre 1/3",
      "description": "",
      "credits": 3,
      "semester": 6,
      "block": "Semestre 6",
      "area": "ELECTIVA",
      "type": "electiva",
      "prerequisites": [],
      "alternatives": []
    },
    {
      "id": "OPT2",
      "code": "OPT 2",
      "title": "Optativa 2/5",
      "description": "",
      "credits": 3,
      "semester": 6,
      "block": "Semestre 6",
      "area": "OPT",
      "type": "optativa",
      "prerequisites": [],
      "alternatives": []
    },
    {
      "id": "PAS4000",
      "code": "PAS 4000",
      "title": "Práctica Pre-Profesional PASEM",
      "description": "",
      "credits": 5,
      "semester": 7,
      "block": "Semestre 7",
      "area": "PAS",
      "type": "obligatoria",
      "prerequisites": [],
      "alternatives": []
    },
    {
      "id": "HSP4002",
      "code": "HSP 4002",
      "title": "Revenue Management",
      "description": "",
      "credits": 3,
      "semester": 8,
      "block": "Semestre 8",
      "area": "HSP",
      "type": "obligatoria",
      "prerequisites": [
        "HSP2001",
        "MAT2009",
        "HSP2002"
      ],
      "alternatives": []
    },
    {
      "id": "OPT3",
      "code": "OPT 3",
      "title": "Optativa 3/5",
      "description": "",
      "credits": 3,
      "semester": 8,
      "block": "Semestre 8",
      "area": "OPT",
      "type": "optativa",
      "prerequisites": [],
      "alternatives": []
    },
    {
      "id": "OPT4",
      "code": "OPT 4",
      "title": "Optativa 4/5",
      "description": "",
      "credits": 3,
      "semester": 8,
      "block": "Semestre 8",
      "area": "OPT",
      "type": "optativa",
      "prerequisites": [],
      "alternatives": []
    },
    {
      "id": "ARTE",
      "code": "ARTE",
      "title": "Arte: ART/MUS/DAN/TEA",
      "description": "",
      "credits": 3,
      "semester": 8,
      "block": "Semestre 8",
      "area": "ARTE",
      "type": "optativa",
      "prerequisites": [],
      "alternatives": []
    },
    {
      "id": "DEP0010",
      "code": "DEP 0010",
      "title": "Deportes",
      "description": "",
      "credits": 1,
      "semester": 9,
      "block": "Semestre 9",
      "area": "DEP",
      "type": "obligatoria",
      "prerequisites": [],
      "alternatives": []
    },
    {
      "id": "ELECTIVA2",
      "code": "ELECTIVA 2",
      "title": "Electiva Libre 2/3",
      "description": "",
      "credits": 3,
      "semester": 9,
      "block": "Semestre 9",
      "area": "ELECTIVA",
      "type": "electiva",
      "prerequisites": [],
      "alternatives": []
    },
    {
      "id": "ELECTIVA3",
      "code": "ELECTIVA 3",
      "title": "Electiva Libre 3/3",
      "description": "",
      "credits": 3,
      "semester": 9,
      "block": "Semestre 9",
      "area": "ELECTIVA",
      "type": "electiva",
      "prerequisites": [],
      "alternatives": []
    },
    {
      "id": "OPT5",
      "code": "OPT 5",
      "title": "Optativa 5/5",
      "description": "",
      "credits": 3,
      "semester": 9,
      "block": "Semestre 9",
      "area": "OPT",
      "type": "optativa",
      "prerequisites": [],
      "alternatives": []
    },
    {
      "id": "HSP4992",
      "code": "HSP 4992",
      "title": "Proyectos Hospitalidad",
      "description": "",
      "credits": 5,
      "semester": 9,
      "block": "Semestre 9",
      "area": "HSP",
      "type": "obligatoria",
      "prerequisites": [
        "HSP4001",
        "HSP2002",
        "HSP3008"
      ],
      "alternatives": []
    }
  ]
}